deprecated/gen_partial.py
deprecated/generate_data copy.py
deprecated/mh copy.py
deprecated/mh_complicated.py
deprecated/mp_utils copy 2.py
deprecated/mp_utils copy.py
deprecated/mp_utils_before_simplify.py
deprecated/mp_utils_complicated.py
deprecated/mp_utils_complicated_copy_20250826.py
deprecated/mp_utils_with_all_njit.py
deprecated/mp_utils_with_rng_shuffle.py
deprecated/run copy.py
pympebm/__init__.py
pympebm/generate_data.py
pympebm/mh copy 2.py
pympebm/mh copy.py
pympebm/mh.py
pympebm/mp_utils.py
pympebm/run copy.py
pympebm/run.py
pympebm/utils copy.py
pympebm/utils.py
pympebm/viz.py
pympebm/copies/mh copy.py
pympebm/copies/mp_utils copy.py
pympebm/copies/utils copy.py
pympebm/data/__init__.py
pympebm/data/params.json
pympebm/data/samples/10|100_0.csv
pympebm/data/samples/5|50_0.csv
pympebm/test/gen.py
pympebm/test/test copy.py
pympebm/test/test.py
pympebm_copy/__init__.py
pympebm_copy/generate_data.py
pympebm_copy/mh.py
pympebm_copy/mp_utils.py
pympebm_copy/run.py
pympebm_copy/utils.py
pympebm_copy/viz.py
pympebm_copy/data/__init__.py
pympebm_copy/test/gen.py
pympebm_copy/test/test.py
pympebm_old/__init__.py
pympebm_old/run.py
pympebm_old/algorithms/__init__.py
pympebm_old/algorithms/algorithm.py
pympebm_old/data/__init__.py
pympebm_old/test/gen.py
pympebm_old/test/gen_partial.py
pympebm_old/test/test.py
pympebm_old/utils/__init__.py
pympebm_old/utils/data_processing.py
pympebm_old/utils/fast_kde.py
pympebm_old/utils/generate_data.py
pympebm_old/utils/kmeans.py
pympebm_old/utils/logging_utils.py
pympebm_old/utils/runners.py
pympebm_old/utils/ucl_gmm.py
pympebm_old/utils/visualization.py
pympebm-0.8.6.dist-info/LICENSE
pympebm-0.8.6.dist-info/METADATA
pympebm-0.8.6.dist-info/WHEEL
pympebm-0.8.6.dist-info/top_level.txt
pympebm-0.8.6.dist-info/RECORD
