Metadata-Version: 2.1
Name: pympebm
Version: 0.8.6
Summary: Mixed-Pathology Event-Based Modeling for Disease Progression
Author-email: Hongtao Hao and Joseph Austerweil <hongtaoh@cs.wisc.edu>
Project-URL: Homepage, https://github.com/hongtaoh/pympebm
Classifier: Programming Language :: Python :: 3
Classifier: License :: OSI Approved :: MIT License
Classifier: Operating System :: OS Independent
Requires-Python: >=3.7
License-File: LICENSE
Requires-Dist: pandas
Requires-Dist: numpy
Requires-Dist: scipy
Requires-Dist: matplotlib
Requires-Dist: seaborn
Requires-Dist: scikit-learn
Requires-Dist: numba
Requires-Dist: pysaebm
